influxdb_influxql_client/__init__.py
influxdb_influxql_client/client/__init__.py
influxdb_influxql_client/client/_base.py
influxdb_influxql_client/client/influxdb_influxql_client.py
influxdb_influxql_client/client/query_api.py
influxdb_influxql_client/client/models/Results.py
influxdb_influxql_client/client/models/__init__.py
influxdb_influxql_client/client/util/__init__.py
influxdb_influxql_client/client/util/request_helper.py
influxql_client-0.0.3.dist-info/LICENSE
influxql_client-0.0.3.dist-info/METADATA
influxql_client-0.0.3.dist-info/WHEEL
influxql_client-0.0.3.dist-info/top_level.txt
influxql_client-0.0.3.dist-info/RECORD
