Metadata-Version: 2.1
Name: influxql_client
Version: 0.0.3
Summary: InfluxDB InfluxQL Basic Library
Home-page: https://github.com/delrey1/influxdb-influxql-client
Keywords: InfluxDB,InfluxDB Python Client,InfluxQL
Classifier: Development Status :: 4 - Beta
Classifier: Intended Audience :: Developers
Classifier: Topic :: Software Development :: Libraries
Classifier: Topic :: Software Development :: Libraries :: Python Modules
Classifier: Programming Language :: Python :: 3.7
Classifier: Programming Language :: Python :: 3.8
Classifier: Programming Language :: Python :: 3.9
Classifier: Programming Language :: Python :: 3.10
Classifier: Programming Language :: Python :: 3.11
Requires-Python: >=3.7
License-File: LICENSE
Requires-Dist: setuptools >=21.0.0
Requires-Dist: requests >=2.28.2
Requires-Dist: pydantic >=2
